[
  {
    "top": true,
    "name": "Reality",
    "albumId": 559469,
    "genre": "댄스&일렉트로닉",
    "start": "2015-07-13",
    "artist": "인피니트"
  },
  {
    "name": "Big Summer Night",
    "albumId": 559878,
    "genre": "록",
    "start": "2015-07-14",
    "artist": "세이수미"
  },
  {
    "name": "Los Amigos 2nd Vamos",
    "albumId": 563184,
    "genre": "재즈&크로스오버",
    "start": "2015-07-23",
    "artist": "로스 아미고스"
  },
  {
    "name": "여자친구 2nd Mini Album `Flower Bud`",
    "albumId": 563176,
    "genre": "댄스&일렉트로닉",
    "start": "2015-07-23",
    "artist": "여자친구"
  },
  {
    "name": "썬파워",
    "albumId": 557556,
    "genre": "모던록",
    "start": "2015-07-07",
    "artist": "구남과여라이딩스텔라"
  },
  {
    "name": "SYX",
    "albumId": 558291,
    "genre": "모던록",
    "start": "2015-07-09",
    "artist": "이승열"
  },
  {
    "name": "The Song Of Songs",
    "albumId": 558165,
    "genre": "팝",
    "start": "2015-07-09",
    "artist": "타루"
  },
  {
    "name": "시원 시원 여름비",
    "albumId": 563508,
    "genre": "팝",
    "start": "2015-07-27",
    "artist": "우쿨렐레 피크닉"
  },
  {
    "name": "(HUMAN COMPLEX) Integrated",
    "albumId": 556694,
    "genre": "록",
    "start": "2015-07-03",
    "artist": "김사랑"
  },
  {
    "name": "등목",
    "albumId": 557975,
    "genre": "모던록",
    "start": "2015-07-08",
    "artist": "후추스"
  },
  {
    "name": "문학소년",
    "albumId": 562047,
    "genre": "포크",
    "start": "2015-07-21",
    "artist": "9"
  },
  {
    "name": "RESPECT",
    "albumId": 559991,
    "genre": "랩&힙합",
    "start": "2015-07-14",
    "artist": "로꼬"
  },
  {
    "name": "The Lake In The City",
    "albumId": 555971,
    "genre": "모던록",
    "start": "2015-07-01",
    "artist": "레이크"
  },
  {
    "name": "Vikini Party",
    "albumId": 555880,
    "genre": "모던록",
    "start": "2015-07-01",
    "artist": "블루아일리즈 "
  },
  {
    "name": "SQ (We Don`t Need No EQ IQ)",
    "albumId": 559813,
    "genre": "록",
    "start": "2015-07-14",
    "artist": "술탄 오브 더 디스코"
  },
  {
    "name": "사랑가",
    "albumId": 564733,
    "genre": "록",
    "start": "2015-07-29",
    "artist": "Various Artists"
  },
  {
    "name": "Brand New Day",
    "albumId": 559279,
    "genre": "락",
    "start": "2015-07-13",
    "artist": "뷰렛"
  },
  {
    "name": "919",
    "albumId": 556723,
    "genre": "록",
    "start": "2015-07-03",
    "artist": "Boys In The Kitchen"
  },
  {
    "name": "Polyverse",
    "albumId": 562019,
    "genre": "록",
    "start": "2015-07-21",
    "artist": "슈가도넛"
  },
  {
    "name": "2-3",
    "albumId": 563626,
    "genre": "알앤비&소울",
    "start": "2015-07-24",
    "artist": "프라이머리"
  },
  {
    "name": "너를 보는 난 여름 (Love Letters)",
    "albumId": 561296,
    "genre": "팝",
    "start": "2015-07-17",
    "artist": "루싸이트 토끼"
  },
  {
    "name": "떨려요",
    "albumId": 561715,
    "genre": "댄스&일렉트로닉",
    "start": "2015-07-20",
    "artist": "스텔라"
  }
]
